pal_app/__init__.py
pal_app/pal_app.py
pal_app-2.1.0.data/data/share/ament_index/resource_index/packages/pal_app
pal_app-2.1.0.data/data/share/pal_app/package.xml
pal_app-2.1.0.data/data/share/pal_app/tpl/apps/python/{{id}}/CMakeLists.txt.j2
pal_app-2.1.0.data/data/share/pal_app/tpl/apps/python/{{id}}/LICENSE.j2
pal_app-2.1.0.data/data/share/pal_app/tpl/apps/python/{{id}}/package.xml.j2
pal_app-2.1.0.data/data/share/pal_app/tpl/mission_ctrls/base_python/{{id}}/LICENSE.j2
pal_app-2.1.0.data/data/share/pal_app/tpl/mission_ctrls/base_python/{{id}}/README.md.j2
pal_app-2.1.0.data/data/share/pal_app/tpl/mission_ctrls/base_python/{{id}}/package.xml.j2
pal_app-2.1.0.data/data/share/pal_app/tpl/mission_ctrls/base_python/{{id}}/setup.cfg.j2
pal_app-2.1.0.data/data/share/pal_app/tpl/mission_ctrls/base_python/{{id}}/setup.py.j2
pal_app-2.1.0.data/data/share/pal_app/tpl/mission_ctrls/base_python/{{id}}/launch/{{id}}.launch.py.j2
pal_app-2.1.0.data/data/share/pal_app/tpl/mission_ctrls/base_python/{{id}}/module/{{id}}.j2
pal_app-2.1.0.data/data/share/pal_app/tpl/mission_ctrls/base_python/{{id}}/module/{{id}}_module.yaml.j2
pal_app-2.1.0.data/data/share/pal_app/tpl/mission_ctrls/base_python/{{id}}/module_set/{{id}}.j2
pal_app-2.1.0.data/data/share/pal_app/tpl/mission_ctrls/base_python/{{id}}/module_set/{{id}}_module_set.yaml.j2
pal_app-2.1.0.data/data/share/pal_app/tpl/mission_ctrls/base_python/{{id}}/pages_only_ari/README.md.j2
pal_app-2.1.0.data/data/share/pal_app/tpl/mission_ctrls/base_python/{{id}}/pages_only_ari/zip_pages.sh.j2
pal_app-2.1.0.data/data/share/pal_app/tpl/mission_ctrls/base_python/{{id}}/pages_only_ari/en_GB/landing_page/index.html.j2
pal_app-2.1.0.data/data/share/pal_app/tpl/mission_ctrls/base_python/{{id}}/pages_only_ari/en_GB/landing_page/js/main.js.j2
pal_app-2.1.0.data/data/share/pal_app/tpl/mission_ctrls/base_python/{{id}}/pages_only_ari/en_GB/landing_page/style/style.css.j2
pal_app-2.1.0.dist-info/LICENSE
pal_app-2.1.0.dist-info/METADATA
pal_app-2.1.0.dist-info/WHEEL
pal_app-2.1.0.dist-info/entry_points.txt
pal_app-2.1.0.dist-info/top_level.txt
pal_app-2.1.0.dist-info/zip-safe
pal_app-2.1.0.dist-info/RECORD
